gitdata/__init__.py
gitdata/__version__.py
gitdata/buckets.py
gitdata/config.py
gitdata/digester.py
gitdata/graphs.py
gitdata/json.py
gitdata/queues.py
gitdata/repositories.py
gitdata/solutions.py
gitdata/sql.py
gitdata/utils.py
gitdata/assets/README.md
gitdata/cli/__init__.py
gitdata/cli/gitdata_get.py
gitdata/cli/gitdata_scan.py
gitdata/connectors/__init__.py
gitdata/connectors/common.py
gitdata/connectors/fake.py
gitdata/connectors/gitlab.py
gitdata/connectors/http.py
gitdata/connectors/local.py
gitdata/database/__init__.py
gitdata/database/common.py
gitdata/database/mysql.py
gitdata/database/mysql_setup.sql
gitdata/database/mysql_setup_test_database.sql
gitdata/database/postgresql.py
gitdata/database/sqlite3.py
gitdata/database/sqlite3_setup.sql
gitdata/database/sqlite3_setup_test_data.sql
gitdata/ext/__init__.py
gitdata/ext/connectors/__init__.py
gitdata/stores/__init__.py
gitdata/stores/common.py
gitdata/stores/entities.py
gitdata/stores/facts.py
gitdata/stores/tables.py
gitdata_lib-0.0.12.dist-info/LICENSE
gitdata_lib-0.0.12.dist-info/METADATA
gitdata_lib-0.0.12.dist-info/WHEEL
gitdata_lib-0.0.12.dist-info/entry_points.txt
gitdata_lib-0.0.12.dist-info/top_level.txt
gitdata_lib-0.0.12.dist-info/RECORD
